pyhipp_sims/data/simulations/eagle.json
pyhipp_sims/data/simulations/eagle_test.json
pyhipp_sims/data/simulations/elucid.json
pyhipp_sims/data/simulations/elucid_ext.json
pyhipp_sims/data/simulations/elucid_ext_v2.json
pyhipp_sims/data/simulations/elucid_w9l3ha.json
pyhipp_sims/data/simulations/elucid_w9l3ha_ext_v2.json
pyhipp_sims/data/simulations/millennium_2_scaled_wmap7.json
pyhipp_sims/data/simulations/sam_mah_z10.json
pyhipp_sims/data/simulations/sam_mah_z25.json
pyhipp_sims/data/simulations/tng.json
pyhipp_sims/data/simulations/tng_300_1.json
pyhipp_sims/data/simulations/tng_50_1.json
pyhipp_sims/data/simulations/tng_dark.json
pyhipp_sims/data/simulations/tng_dark_100_3.json
pyhipp_sims/data/simulations/tng_dark_300_1.json
pyhipp_sims/data/simulations/tng_dark_300_3.json
pyhipp_sims/data/simulations/tng_dark_50_3.json
pyhipp_sims/sims/__init__.py
pyhipp_sims/sims/abc.py
pyhipp_sims/sims/groups.py
pyhipp_sims/sims/sim_info.py
pyhipp_sims/sims/snapshots.py
pyhipp_sims/sims/trees.py
pyhipp_sims-1.0.1.dist-info/LICENSE
pyhipp_sims-1.0.1.dist-info/METADATA
pyhipp_sims-1.0.1.dist-info/WHEEL
pyhipp_sims-1.0.1.dist-info/top_level.txt
pyhipp_sims-1.0.1.dist-info/RECORD
